{
  "button": [
    {
      "name": "课程中心",
      "sub_button": [
        {
          "type": "view",
          "name": "课程介绍",
          "url": "http://guogin.ngrok.io/user/aboutcourse",
          "sub_button": []
        },
        {
          "type": "view",
          "name": "课程预约",
          "url": "http://guogin.ngrok.io/user/reservecourse",
          "sub_button": []
        },
        {
          "type": "view",
          "name": "我的课程",
          "url": "http://guogin.ngrok.io/user/course",
          "sub_button": []
        }
      ]
    },
    {
      "name": "个人中心",
      "sub_button": [
        {
          "type": "view",
          "name": "我的作品",
          "url": "http://guogin.ngrok.io/user/relatedimage",
          "sub_button": []
        },
        {
          "type": "view",
          "name": "衍生商品",
          "url": "http://guogin.ngrok.io/user/imagecollection",
          "sub_button": []
        },
        {
          "type": "view",
          "name": "我就是我",
          "url": "http://guogin.ngrok.io/user/signin",
          "sub_button": []
        }
      ]
    },
    {
      "name": "大树夏",
      "sub_button": [
        {
          "type": "view",
          "name": "购物车",
          "url": "http://guogin.ngrok.io/user/cart",
          "sub_button": []
        },
        {
          "type": "view",
          "name": "看订单",
          "url": "http://guogin.ngrok.io/user/orderList",
          "sub_button": []
        },
        {
          "type": "view",
          "name": "传图片",
          "url": "http://guogin.ngrok.io/manager/search",
          "sub_button": []
        },
        {
          "type": "view",
          "name": "关于我们",
          "url": "http://guogin.ngrok.io/site/about",
          "sub_button": []
        }
      ]
    }
  ]
}